.gitignore
CHANGELOG.rst
CONTRIBUTING.md
LICENSE.txt
MANIFEST.in
README.md
pyproject.toml
tox.ini
src/entitysdk/__init__.py
src/entitysdk/_server_schemas.py
src/entitysdk/client.py
src/entitysdk/common.py
src/entitysdk/config.py
src/entitysdk/core.py
src/entitysdk/exception.py
src/entitysdk/mixin.py
src/entitysdk/result.py
src/entitysdk/route.py
src/entitysdk/serdes.py
src/entitysdk/store.py
src/entitysdk/token_manager.py
src/entitysdk/types.py
src/entitysdk/util.py
src/entitysdk/dependencies/__init__.py
src/entitysdk/dependencies/entity.py
src/entitysdk/downloaders/__init__.py
src/entitysdk/downloaders/cell_morphology.py
src/entitysdk/downloaders/em_cell_mesh.py
src/entitysdk/downloaders/emodel.py
src/entitysdk/downloaders/ion_channel_model.py
src/entitysdk/downloaders/memodel.py
src/entitysdk/downloaders/simulation.py
src/entitysdk/downloaders/simulation_result.py
src/entitysdk/models/__init__.py
src/entitysdk/models/activity.py
src/entitysdk/models/analysis_notebook_environment.py
src/entitysdk/models/analysis_notebook_execution.py
src/entitysdk/models/analysis_notebook_result.py
src/entitysdk/models/analysis_notebook_template.py
src/entitysdk/models/asset.py
src/entitysdk/models/base.py
src/entitysdk/models/brain_atlas.py
src/entitysdk/models/brain_atlas_region.py
src/entitysdk/models/brain_location.py
src/entitysdk/models/brain_region.py
src/entitysdk/models/brain_region_hierarchy.py
src/entitysdk/models/cell_morphology.py
src/entitysdk/models/cell_morphology_protocol.py
src/entitysdk/models/circuit.py
src/entitysdk/models/circuit_extraction.py
src/entitysdk/models/classification.py
src/entitysdk/models/contribution.py
src/entitysdk/models/core.py
src/entitysdk/models/derivation.py
src/entitysdk/models/electrical_cell_recording.py
src/entitysdk/models/electrical_recording.py
src/entitysdk/models/em_cell_mesh.py
src/entitysdk/models/em_dense_reconstruction_dataset.py
src/entitysdk/models/emodel.py
src/entitysdk/models/entity.py
src/entitysdk/models/etype.py
