Metadata-Version: 2.4
Name: entitysdk
Version: 0.11.2
Summary: Python library for interacting with the entitycore service
Author-email: Open Brain Institute <info@openbraininstitute.org>
Maintainer-email: Open Brain Institute <info@openbraininstitute.org>
License-Expression: Apache-2.0
Project-URL: documentation, https://entitysdk.readthedocs.io/en/stable
Project-URL: repository, https://github.com/openbraininstitute/entitysdk
Project-URL: changelog, https://github.com/openbraininstitute/entitysdk/CHANGELOG.md
Classifier: Programming Language :: Python :: 3.10
Classifier: Programming Language :: Python :: 3.11
Classifier: Programming Language :: Python :: 3.12
Classifier: Programming Language :: Python :: 3.13
Requires-Python: >=3.10
License-File: LICENSE.txt
Requires-Dist: httpx
Requires-Dist: pydantic>=2.12.0
Requires-Dist: pydantic-settings
Requires-Dist: typing_extensions; python_version < "3.12"
Requires-Dist: backports.strenum; python_version < "3.11"
Provides-Extra: staging
Requires-Dist: h5py; extra == "staging"
Dynamic: license-file
